{"links":[{"id":"a964ac52-f4ab-44b5-b8e9-f606b226412c","source":"b1a51f05-67d9-48ce-a731-c0ff4056c2ac","target":"d32738df-a6ba-4d50-a3d6-6bc9725eee12","properties":{"type":"maestro-link","maestro-link":{}}},{"id":"56467e5d-3694-4a1f-a33d-2c9d4155fad9","source":"b1a51f05-67d9-48ce-a731-c0ff4056c2ac","target":"fa7c0b2a-965c-42cc-bffe-6e50918c2dcd","properties":{"type":"model-type-link","model-type-link":{}}}],"nodes":[{"id":"b1a51f05-67d9-48ce-a731-c0ff4056c2ac","dirty":{"nodeType":true,"Pinned":true,"text":true,"view-package":true,"codeUser":true},"propertyVersions":{"text":2,"nodeType":1,"Pinned":5,"codeName":1,"agentName":1,"valueName":1,"cssName":1,"HttpRoute":1,"uiName":1,"Label":1,"view-package":1,"codeUser":1},"properties":{"text":"Payment History Controller","nodeType":"controller","Pinned":false,"codeName":"PaymentHistoryController","agentName":"PaymentHistoryController","valueName":"PaymentHistoryController","cssName":"payment-history-controller","HttpRoute":"payment/history/controller","uiName":"Payment History Controller","Label":"Payment History Controller","view-package":"fd4a81f9-03c3-47af-ab9f-7ed2e19f4232","codeUser":"systemUser"}},{"id":"d32738df-a6ba-4d50-a3d6-6bc9725eee12","dirty":{"nodeType":true,"Pinned":true,"text":true,"view-package":true},"propertyVersions":{"text":2,"nodeType":1,"Pinned":5,"codeName":1,"agentName":1,"valueName":1,"cssName":1,"HttpRoute":1,"uiName":1,"Label":1,"view-package":1},"properties":{"text":"Payment History Maestro","nodeType":"maestro","Pinned":false,"codeName":"PaymentHistoryMaestro","agentName":"PaymentHistoryMaestro","valueName":"PaymentHistoryMaestro","cssName":"payment-history-maestro","HttpRoute":"payment/history/maestro","uiName":"Payment History Maestro","Label":"Payment History Maestro","view-package":"fd4a81f9-03c3-47af-ab9f-7ed2e19f4232"}},{"id":"fa7c0b2a-965c-42cc-bffe-6e50918c2dcd","dirty":{"text":true,"nodeType":true,"groups":true,"AgentBasedMethod":true,"Pinned":true},"propertyVersions":{"text":2,"codeName":1,"agentName":1,"valueName":1,"cssName":1,"HttpRoute":1,"uiName":1,"Label":1,"nodeType":2,"groups":1,"AgentBasedMethod":2,"Pinned":9},"properties":{"text":"Payment History","codeName":"PaymentHistory","agentName":"PaymentHistory","valueName":"PaymentHistory","cssName":"payment-history","HttpRoute":"payment/history","uiName":"Payment History","Label":"Payment History","nodeType":"model","groups":{"group":"a4f0fc5c-5fb6-4b0c-a4a4-99f4b6b59274"},"Pinned":false,"AgentBasedMethod":false}}]}