{"links":[{"id":"f08661ad-4861-4a35-bfab-46ffa9028041","source":"d11ff5b6-feef-485f-844c-1e29c4e60b1b","target":"b5c4d2ba-62f8-43c8-92a1-eacb64d5a058","properties":{"type":"maestro-link","maestro-link":{}}},{"id":"698eda26-fccf-400f-aa61-0a33ad1f1861","source":"b5c4d2ba-62f8-43c8-92a1-eacb64d5a058","target":"c5d37e30-64f7-49d7-983b-5bbbe088d470","properties":{"type":"function-link","function-link":{}}},{"id":"2b1764da-7f26-4b5f-bb1e-44d412ce294b","source":"c7fe8eda-6132-4679-bc9a-2c1a7accf560","target":"b5c4d2ba-62f8-43c8-92a1-eacb64d5a058","properties":{"type":"function-link","function-link":{}}},{"id":"132adb79-66b3-4dc2-a4df-1e907349ccae","source":"b5c4d2ba-62f8-43c8-92a1-eacb64d5a058","target":"44eba7c8-466e-4e74-92a9-dee17bcfa873","properties":{"type":"model-type-link","model-type-link":{}}}],"nodes":[{"id":"b5c4d2ba-62f8-43c8-92a1-eacb64d5a058","dirty":{"nodeType":true,"Pinned":true,"text":true,"view-package":true,"Selected":true},"propertyVersions":{"text":2,"nodeType":1,"Pinned":6,"codeName":1,"agentName":1,"valueName":1,"cssName":1,"HttpRoute":1,"uiName":1,"Label":1,"view-package":1,"Selected":2},"properties":{"text":"Media Customizations Maestro","nodeType":"maestro","Pinned":false,"codeName":"MediaCustomizationsMaestro","agentName":"MediaCustomizationsMaestro","valueName":"MediaCustomizationsMaestro","cssName":"media-customizations-maestro","HttpRoute":"media/customizations/maestro","uiName":"Media Customizations Maestro","Label":"Media Customizations Maestro","view-package":"404f34b4-140b-4eef-95e1-4909577100a0","Selected":false}},{"id":"d11ff5b6-feef-485f-844c-1e29c4e60b1b","dirty":{"nodeType":true,"Pinned":true,"text":true,"view-package":true,"codeUser":true},"propertyVersions":{"text":2,"nodeType":1,"Pinned":4,"codeName":1,"agentName":1,"valueName":1,"cssName":1,"HttpRoute":1,"uiName":1,"Label":1,"view-package":1,"codeUser":1},"properties":{"text":"Media Customizations Controller","nodeType":"controller","Pinned":false,"codeName":"MediaCustomizationsController","agentName":"MediaCustomizationsController","valueName":"MediaCustomizationsController","cssName":"media-customizations-controller","HttpRoute":"media/customizations/controller","uiName":"Media Customizations Controller","Label":"Media Customizations Controller","view-package":"404f34b4-140b-4eef-95e1-4909577100a0","codeUser":"systemUser"}},{"id":"c5d37e30-64f7-49d7-983b-5bbbe088d470","dirty":{"text":true,"nodeType":true,"groups":true,"Selected":true,"Pinned":true},"propertyVersions":{"text":2,"codeName":1,"agentName":1,"valueName":1,"cssName":1,"HttpRoute":1,"uiName":1,"Label":1,"nodeType":2,"groups":1,"Selected":2,"Pinned":3},"properties":{"text":"Publish Media Customizations","codeName":"PublishMediaCustomizations","agentName":"PublishMediaCustomizations","valueName":"PublishMediaCustomizations","cssName":"publish-media-customizations","HttpRoute":"publish/media/customizations","uiName":"Publish Media Customizations","Label":"Publish Media Customizations","nodeType":"function","groups":{"group":"86918280-c5d5-4601-a6f0-28aca70f5bdf"},"Selected":false,"Pinned":false}},{"id":"c7fe8eda-6132-4679-bc9a-2c1a7accf560","dirty":{"nodeType":true,"Pinned":true,"text":true,"Agent":true,"Maestro":true,"Model":true,"groups":true},"propertyVersions":{"text":2,"nodeType":1,"Pinned":2,"codeName":1,"agentName":1,"valueName":1,"cssName":1,"HttpRoute":1,"uiName":1,"Label":1,"Agent":1,"Maestro":1,"Model":1,"groups":1},"properties":{"text":"Set Media Customizations For Profile","nodeType":"function","Pinned":false,"codeName":"SetMediaCustomizationsForProfile","agentName":"SetMediaCustomizationsForProfile","valueName":"SetMediaCustomizationsForProfile","cssName":"set-media-customizations-for-profile","HttpRoute":"set/media/customizations/for/profile","uiName":"Set Media Customizations For Profile","Label":"Set Media Customizations For Profile","Agent":"b6bf495b-9547-41b7-9025-71f22f7f9e1f","Maestro":"b5c4d2ba-62f8-43c8-92a1-eacb64d5a058","Model":"44eba7c8-466e-4e74-92a9-dee17bcfa873","groups":{"group":"a8a49e7d-7ec9-40db-9b83-27163ff0dbce"}}},{"id":"44eba7c8-466e-4e74-92a9-dee17bcfa873","dirty":{"text":true,"nodeType":true,"groups":true,"hasLogicalChildren":true,"logicalChildrenTypes":true,"Pinned":true,"AgentBasedMethod":true},"propertyVersions":{"text":2,"codeName":1,"agentName":1,"valueName":1,"cssName":1,"HttpRoute":1,"uiName":1,"Label":1,"nodeType":2,"groups":1,"hasLogicalChildren":1,"logicalChildrenTypes":2,"Pinned":10,"AgentBasedMethod":2},"properties":{"text":"Media Customizations","codeName":"MediaCustomizations","agentName":"MediaCustomizations","valueName":"MediaCustomizations","cssName":"media-customizations","HttpRoute":"media/customizations","uiName":"Media Customizations","Label":"Media Customizations","nodeType":"model","groups":{"group":"b423cf54-2dab-4025-8ca7-4fa60b2a99d1"},"hasLogicalChildren":true,"logicalChildrenTypes":[],"Pinned":false,"AgentBasedMethod":false}}]}