{"links":[{"id":"0c65b914-ede3-45d2-8a94-62c5e3439468","source":"f3f82b88-d06e-44d5-b63e-14ec5059c2ab","target":"168ea02e-5f3a-4c33-8328-534d769dea39","properties":{"type":"function-operator","function-operator":{}}},{"id":"6ffceee9-3f4a-4fd9-95cf-d718f717314e","source":"f3f82b88-d06e-44d5-b63e-14ec5059c2ab","target":"18094b11-9ff7-4f6f-b8ee-4868d39f73d6","properties":{"type":"function-operator","function-operator":{}}},{"id":"ae96915c-e39d-41bb-bb2a-0b75fa81ba65","source":"f3f82b88-d06e-44d5-b63e-14ec5059c2ab","target":"54849a06-d06b-4efd-a34d-9e51e6637425","properties":{"type":"function-operator","function-operator":{}}},{"id":"be631b65-372d-401c-bd5d-a4b7555b9c5a","source":"f3f82b88-d06e-44d5-b63e-14ec5059c2ab","target":"548338bf-0ff3-4c78-a991-cbf70165f7d8","properties":{"type":"function-operator","function-operator":{}}},{"id":"4ca59386-86a3-4030-bb90-962b010f3cfd","source":"f3f82b88-d06e-44d5-b63e-14ec5059c2ab","target":"8f2cd8ce-c491-42d9-a06f-50e41a237d03","properties":{"type":"function-operator","function-operator":{}}}],"nodes":[{"id":"f3f82b88-d06e-44d5-b63e-14ec5059c2ab","dirty":{"nodeType":true,"Pinned":true,"NodePackage":true,"NodePackageType":true,"NodePackageAgent":true,"functionType":true,"MethodType":true,"HttpMethod":true,"text":true,"view-package":true,"groupParent":true,"methodProperties":true,"groups":true},"propertyVersions":{"text":2,"nodeType":1,"Pinned":2,"NodePackage":1,"NodePackageType":1,"NodePackageAgent":1,"functionType":1,"MethodType":1,"HttpMethod":1,"codeName":1,"agentName":1,"valueName":1,"cssName":1,"HttpRoute":1,"uiName":1,"Label":1,"view-package":1,"groupParent":1,"methodProperties":3,"groups":1},"properties":{"text":"Get Release Schedule Actions by Player Return List","nodeType":"method","Pinned":false,"NodePackage":null,"NodePackageType":"Get Release Schedule Actions by Player Return List","NodePackageAgent":"18094b11-9ff7-4f6f-b8ee-4868d39f73d6","functionType":"Get/Object/Agent/Value => IList<Object>","MethodType":"GetAll","HttpMethod":"HttpPost","codeName":"GetReleaseScheduleActionsbyPlayerReturnList","agentName":"GetReleaseScheduleActionsbyPlayerReturnList","valueName":"GetReleaseScheduleActionsbyPlayerReturnList","cssName":"get-release-schedule-actions-by-player-return-list","HttpRoute":"get/release/schedule/actions/by/player/return/list","uiName":"Get Release Schedule Actions by Player Return List","Label":"Get Release Schedule Actions by Player Return List","view-package":"624293aa-2635-4206-abb7-62fc66e92ed7","groupParent":"a66f0bf6-0121-4b05-8bf4-8fa290170d78","methodProperties":{"model":"168ea02e-5f3a-4c33-8328-534d769dea39","model_output":"168ea02e-5f3a-4c33-8328-534d769dea39","agent":"18094b11-9ff7-4f6f-b8ee-4868d39f73d6","user":"54849a06-d06b-4efd-a34d-9e51e6637425","permission":"548338bf-0ff3-4c78-a991-cbf70165f7d8","model_filter":"8f2cd8ce-c491-42d9-a06f-50e41a237d03"},"groups":{"group":"14acd296-3467-4fd9-92f5-70f9d26eba20"}}},{"id":"168ea02e-5f3a-4c33-8328-534d769dea39","dirty":{"text":true,"nodeType":true,"groups":true,"Pinned":true,"AgentBasedMethod":true},"propertyVersions":{"text":2,"codeName":1,"agentName":1,"valueName":1,"cssName":1,"HttpRoute":1,"uiName":1,"Label":1,"nodeType":2,"groups":1,"Pinned":4,"AgentBasedMethod":1},"properties":{"text":"Release Schedule Action","codeName":"ReleaseScheduleAction","agentName":"ReleaseScheduleAction","valueName":"ReleaseScheduleAction","cssName":"release-schedule-action","HttpRoute":"release/schedule/action","uiName":"Release Schedule Action","Label":"Release Schedule Action","nodeType":"model","groups":{"group":"99d82fb7-d809-4a6f-88f5-0412ade17dc5"},"Pinned":false,"AgentBasedMethod":true}},{"id":"18094b11-9ff7-4f6f-b8ee-4868d39f73d6","dirty":{"text":true,"nodeType":true,"groups":true,"Pinned":true,"isAgent":true,"uiUser":true,"AgentBasedMethod":true},"propertyVersions":{"text":2,"codeName":1,"agentName":1,"valueName":1,"cssName":1,"HttpRoute":1,"uiName":1,"Label":1,"nodeType":2,"groups":1,"Pinned":12,"isAgent":1,"uiUser":1,"AgentBasedMethod":1},"properties":{"text":"Player","codeName":"Player","agentName":"Player","valueName":"Player","cssName":"player","HttpRoute":"player","uiName":"Player","Label":"Player","nodeType":"model","groups":{"group":"1c50b4d4-7e79-4ec1-8705-279a4367919c"},"Pinned":false,"isAgent":true,"uiUser":"54849a06-d06b-4efd-a34d-9e51e6637425","AgentBasedMethod":true}},{"id":"54849a06-d06b-4efd-a34d-9e51e6637425","dirty":{"nodeType":true,"Pinned":true,"text":true,"IsUser":true,"isAgent":true,"uiUser":true},"propertyVersions":{"text":2,"nodeType":1,"Pinned":15,"codeName":1,"agentName":1,"valueName":1,"cssName":1,"HttpRoute":1,"uiName":1,"Label":1,"IsUser":1,"isAgent":1,"uiUser":1},"properties":{"text":"User","nodeType":"model","Pinned":false,"codeName":"User","agentName":"User","valueName":"User","cssName":"user","HttpRoute":"user","uiName":"User","Label":"User","IsUser":true,"isAgent":true,"uiUser":"54849a06-d06b-4efd-a34d-9e51e6637425"}},{"id":"548338bf-0ff3-4c78-a991-cbf70165f7d8","dirty":{"nodeType":true,"Pinned":true,"NodePackage":true,"NodePackageType":true,"text":true,"view-package":true,"groupParent":true},"propertyVersions":{"text":2,"nodeType":1,"Pinned":2,"NodePackage":1,"NodePackageType":1,"codeName":1,"agentName":1,"valueName":1,"cssName":1,"HttpRoute":1,"uiName":1,"Label":1,"view-package":1,"groupParent":1},"properties":{"text":"Get Release Schedule Actions by Player Return List permission","nodeType":"permission","Pinned":false,"NodePackage":"168ea02e-5f3a-4c33-8328-534d769dea39","NodePackageType":"Get Release Schedule Actions by Player Return List","codeName":"GetReleaseScheduleActionsbyPlayerReturnListpermission","agentName":"GetReleaseScheduleActionsbyPlayerReturnListpermission","valueName":"GetReleaseScheduleActionsbyPlayerReturnListpermission","cssName":"get-release-schedule-actions-by-player-return-list-permission","HttpRoute":"get/release/schedule/actions/by/player/return/list/permission","uiName":"Get Release Schedule Actions by Player Return List permission","Label":"Get Release Schedule Actions by Player Return List permission","view-package":"624293aa-2635-4206-abb7-62fc66e92ed7","groupParent":"14acd296-3467-4fd9-92f5-70f9d26eba20"}},{"id":"8f2cd8ce-c491-42d9-a06f-50e41a237d03","dirty":{"nodeType":true,"Pinned":true,"NodePackage":true,"NodePackageType":true,"text":true,"view-package":true,"groupParent":true,"filteragent":true,"filtermodel":true},"propertyVersions":{"text":2,"nodeType":1,"Pinned":2,"NodePackage":1,"NodePackageType":1,"codeName":1,"agentName":1,"valueName":1,"cssName":1,"HttpRoute":1,"uiName":1,"Label":1,"view-package":1,"groupParent":1,"filteragent":1,"filtermodel":1},"properties":{"text":"Get Release Schedule Actions by Player Return List model-filter","nodeType":"model-filter","Pinned":false,"NodePackage":"168ea02e-5f3a-4c33-8328-534d769dea39","NodePackageType":"Get Release Schedule Actions by Player Return List","codeName":"GetReleaseScheduleActionsbyPlayerReturnListmodelfilter","agentName":"GetReleaseScheduleActionsbyPlayerReturnListmodelfilter","valueName":"GetReleaseScheduleActionsbyPlayerReturnListmodelfilter","cssName":"get-release-schedule-actions-by-player-return-list-modelfilter","HttpRoute":"get/release/schedule/actions/by/player/return/list/model-filter","uiName":"Get Release Schedule Actions by Player Return List model-filter","Label":"Get Release Schedule Actions by Player Return List model-filter","view-package":"624293aa-2635-4206-abb7-62fc66e92ed7","groupParent":"14acd296-3467-4fd9-92f5-70f9d26eba20","filteragent":"18094b11-9ff7-4f6f-b8ee-4868d39f73d6","filtermodel":"168ea02e-5f3a-4c33-8328-534d769dea39"}}]}