{"links":[{"id":"6ee4237b-2782-4945-9129-d363bcb73785","source":"086defc9-0339-4b45-bc96-5d522eaef1da","target":"86cddcef-d83b-420b-a6f5-4e7b82e09eb0","properties":{"type":"function-operator","function-operator":{}}},{"id":"681ccc30-19f6-4b2e-ac2b-f85ce686e5ec","source":"086defc9-0339-4b45-bc96-5d522eaef1da","target":"18094b11-9ff7-4f6f-b8ee-4868d39f73d6","properties":{"type":"function-operator","function-operator":{}}},{"id":"d47185ab-8a14-45f3-8c9c-6dcc9bda73e9","source":"086defc9-0339-4b45-bc96-5d522eaef1da","target":"54849a06-d06b-4efd-a34d-9e51e6637425","properties":{"type":"function-operator","function-operator":{}}},{"id":"1aa3cbc9-4194-4828-9729-64d1d6ec4f0f","source":"086defc9-0339-4b45-bc96-5d522eaef1da","target":"a66f3588-11af-4d01-8f3d-368113198089","properties":{"type":"function-operator","function-operator":{}}},{"id":"b9cbeb69-23c9-48e1-b956-8950d3b1a9da","source":"086defc9-0339-4b45-bc96-5d522eaef1da","target":"2dfa11f3-1322-4c3f-ab58-78dd6a7a811b","properties":{"type":"function-operator","function-operator":{}}}],"nodes":[{"id":"086defc9-0339-4b45-bc96-5d522eaef1da","dirty":{"nodeType":true,"Pinned":true,"NodePackage":true,"NodePackageType":true,"NodePackageAgent":true,"functionType":true,"MethodType":true,"HttpMethod":true,"text":true,"view-package":true,"groupParent":true,"methodProperties":true,"groups":true},"propertyVersions":{"text":2,"nodeType":1,"Pinned":2,"NodePackage":1,"NodePackageType":1,"NodePackageAgent":1,"functionType":1,"MethodType":1,"HttpMethod":1,"codeName":1,"agentName":1,"valueName":1,"cssName":1,"HttpRoute":1,"uiName":1,"Label":1,"view-package":1,"groupParent":1,"methodProperties":3,"groups":1},"properties":{"text":"Get Playlists by Player Return List","nodeType":"method","Pinned":false,"NodePackage":null,"NodePackageType":"Get Playlists by Player Return List","NodePackageAgent":"18094b11-9ff7-4f6f-b8ee-4868d39f73d6","functionType":"Get/Object/Agent/Value => IList<Object>","MethodType":"GetAll","HttpMethod":"HttpPost","codeName":"GetPlaylistsbyPlayerReturnList","agentName":"GetPlaylistsbyPlayerReturnList","valueName":"GetPlaylistsbyPlayerReturnList","cssName":"get-playlists-by-player-return-list","HttpRoute":"get/playlists/by/player/return/list","uiName":"Get Playlists by Player Return List","Label":"Get Playlists by Player Return List","view-package":"212dcbf9-c1ec-4fe9-9d99-80f0411752d6","groupParent":"87b3476e-843b-42f9-82ef-be80e227362e","methodProperties":{"model":"86cddcef-d83b-420b-a6f5-4e7b82e09eb0","model_output":"86cddcef-d83b-420b-a6f5-4e7b82e09eb0","agent":"18094b11-9ff7-4f6f-b8ee-4868d39f73d6","user":"54849a06-d06b-4efd-a34d-9e51e6637425","permission":"a66f3588-11af-4d01-8f3d-368113198089","model_filter":"2dfa11f3-1322-4c3f-ab58-78dd6a7a811b"},"groups":{"group":"81b5dbeb-b1a8-4d08-bcc7-3edff9f3c494"}}},{"id":"86cddcef-d83b-420b-a6f5-4e7b82e09eb0","dirty":{"text":true,"nodeType":true,"groups":true,"Pinned":true,"hasLogicalChildren":true,"logicalChildrenTypes":true,"AgentBasedMethod":true},"propertyVersions":{"text":2,"codeName":1,"agentName":1,"valueName":1,"cssName":1,"HttpRoute":1,"uiName":1,"Label":1,"nodeType":2,"groups":1,"Pinned":10,"hasLogicalChildren":1,"logicalChildrenTypes":3,"AgentBasedMethod":1},"properties":{"text":"Playlist","codeName":"Playlist","agentName":"Playlist","valueName":"Playlist","cssName":"playlist","HttpRoute":"playlist","uiName":"Playlist","Label":"Playlist","nodeType":"model","groups":{"group":"4eb3bb6c-e056-44a1-a4d8-548ddafca897"},"Pinned":false,"hasLogicalChildren":true,"logicalChildrenTypes":["08a35a4c-1bc3-4374-a93a-8775b1e16750","69989b9a-e188-410e-8b1e-d3266648a8e0","45f1f2a4-e662-49d7-90f7-7f68067a2a68"],"AgentBasedMethod":true}},{"id":"18094b11-9ff7-4f6f-b8ee-4868d39f73d6","dirty":{"text":true,"nodeType":true,"groups":true,"Pinned":true,"isAgent":true,"uiUser":true,"AgentBasedMethod":true},"propertyVersions":{"text":2,"codeName":1,"agentName":1,"valueName":1,"cssName":1,"HttpRoute":1,"uiName":1,"Label":1,"nodeType":2,"groups":1,"Pinned":12,"isAgent":1,"uiUser":1,"AgentBasedMethod":1},"properties":{"text":"Player","codeName":"Player","agentName":"Player","valueName":"Player","cssName":"player","HttpRoute":"player","uiName":"Player","Label":"Player","nodeType":"model","groups":{"group":"1c50b4d4-7e79-4ec1-8705-279a4367919c"},"Pinned":false,"isAgent":true,"uiUser":"54849a06-d06b-4efd-a34d-9e51e6637425","AgentBasedMethod":true}},{"id":"54849a06-d06b-4efd-a34d-9e51e6637425","dirty":{"nodeType":true,"Pinned":true,"text":true,"IsUser":true,"isAgent":true,"uiUser":true},"propertyVersions":{"text":2,"nodeType":1,"Pinned":15,"codeName":1,"agentName":1,"valueName":1,"cssName":1,"HttpRoute":1,"uiName":1,"Label":1,"IsUser":1,"isAgent":1,"uiUser":1},"properties":{"text":"User","nodeType":"model","Pinned":false,"codeName":"User","agentName":"User","valueName":"User","cssName":"user","HttpRoute":"user","uiName":"User","Label":"User","IsUser":true,"isAgent":true,"uiUser":"54849a06-d06b-4efd-a34d-9e51e6637425"}},{"id":"a66f3588-11af-4d01-8f3d-368113198089","dirty":{"nodeType":true,"Pinned":true,"NodePackage":true,"NodePackageType":true,"text":true,"view-package":true,"groupParent":true},"propertyVersions":{"text":2,"nodeType":1,"Pinned":2,"NodePackage":1,"NodePackageType":1,"codeName":1,"agentName":1,"valueName":1,"cssName":1,"HttpRoute":1,"uiName":1,"Label":1,"view-package":1,"groupParent":1},"properties":{"text":"Get Playlists by Player Return List permission","nodeType":"permission","Pinned":false,"NodePackage":"86cddcef-d83b-420b-a6f5-4e7b82e09eb0","NodePackageType":"Get Playlists by Player Return List","codeName":"GetPlaylistsbyPlayerReturnListpermission","agentName":"GetPlaylistsbyPlayerReturnListpermission","valueName":"GetPlaylistsbyPlayerReturnListpermission","cssName":"get-playlists-by-player-return-list-permission","HttpRoute":"get/playlists/by/player/return/list/permission","uiName":"Get Playlists by Player Return List permission","Label":"Get Playlists by Player Return List permission","view-package":"212dcbf9-c1ec-4fe9-9d99-80f0411752d6","groupParent":"81b5dbeb-b1a8-4d08-bcc7-3edff9f3c494"}},{"id":"2dfa11f3-1322-4c3f-ab58-78dd6a7a811b","dirty":{"nodeType":true,"Pinned":true,"NodePackage":true,"NodePackageType":true,"text":true,"view-package":true,"groupParent":true,"filteragent":true,"filtermodel":true},"propertyVersions":{"text":2,"nodeType":1,"Pinned":2,"NodePackage":1,"NodePackageType":1,"codeName":1,"agentName":1,"valueName":1,"cssName":1,"HttpRoute":1,"uiName":1,"Label":1,"view-package":1,"groupParent":1,"filteragent":1,"filtermodel":1},"properties":{"text":"Get Playlists by Player Return List model-filter","nodeType":"model-filter","Pinned":false,"NodePackage":"86cddcef-d83b-420b-a6f5-4e7b82e09eb0","NodePackageType":"Get Playlists by Player Return List","codeName":"GetPlaylistsbyPlayerReturnListmodelfilter","agentName":"GetPlaylistsbyPlayerReturnListmodelfilter","valueName":"GetPlaylistsbyPlayerReturnListmodelfilter","cssName":"get-playlists-by-player-return-list-modelfilter","HttpRoute":"get/playlists/by/player/return/list/model-filter","uiName":"Get Playlists by Player Return List model-filter","Label":"Get Playlists by Player Return List model-filter","view-package":"212dcbf9-c1ec-4fe9-9d99-80f0411752d6","groupParent":"81b5dbeb-b1a8-4d08-bcc7-3edff9f3c494","filteragent":"18094b11-9ff7-4f6f-b8ee-4868d39f73d6","filtermodel":"86cddcef-d83b-420b-a6f5-4e7b82e09eb0"}}]}