{"links":[{"id":"ee5f5cc6-895b-4ad3-a869-fec63c2f98e4","source":"c7716eaa-25f1-4cfc-857f-190d34ef62a5","target":"47e15dca-756b-48f4-a7b8-11eaec6d207b","properties":{"type":"property-link","property-link":{}}},{"id":"ada4092e-c4ed-434e-a263-1cfa948a63f2","source":"c7716eaa-25f1-4cfc-857f-190d34ef62a5","target":"043ab222-348b-442f-b07e-26c523bbf975","properties":{"type":"property-link","property-link":{}}},{"id":"6498478b-f900-438e-b8e2-d57037a9edf5","source":"c7716eaa-25f1-4cfc-857f-190d34ef62a5","target":"b7744016-972b-4876-b64a-4e04181cec32","properties":{"type":"property-link","property-link":{}}},{"id":"2b8d8d0c-42b6-4ad6-ab08-bfdbc8c3031f","source":"c7716eaa-25f1-4cfc-857f-190d34ef62a5","target":"c6721c7e-fed8-494f-8382-0e986758f7b2","properties":{"type":"property-link","property-link":{}}},{"id":"1ba70dff-b7a8-43e1-b472-cbe7cf2650e6","source":"c7716eaa-25f1-4cfc-857f-190d34ef62a5","target":"87266e30-0b5e-4589-b217-62f1ae1b1e3a","properties":{"type":"property-link","property-link":{}}},{"id":"ecefc990-1d37-4f69-b1a5-ceb808d55aeb","source":"c7716eaa-25f1-4cfc-857f-190d34ef62a5","target":"a0bcffa7-d528-4d54-918f-b92fa1475372","properties":{"type":"property-link","property-link":{}}},{"id":"df0825e8-7631-4e8e-af0d-7dba73cd31d1","source":"c7716eaa-25f1-4cfc-857f-190d34ef62a5","target":"27d9c6d8-0911-4c22-aeac-a426be4296c4","properties":{"type":"property-link","property-link":{}}},{"id":"c167ff2c-5a77-4c29-ac2e-f907ba8aceb7","source":"c7716eaa-25f1-4cfc-857f-190d34ef62a5","target":"04b1c412-dea0-4b83-ac10-3eb09b9fdd1e","properties":{"type":"property-link","property-link":{}}},{"id":"a86ca884-e2ee-4905-b366-69c850ae7e05","source":"043ab222-348b-442f-b07e-26c523bbf975","target":"1e55982c-0b6b-45c9-a250-1802f4269802","properties":{"type":"attribute-link","attribute-link":{}}}],"nodes":[{"id":"c7716eaa-25f1-4cfc-857f-190d34ef62a5","dirty":{"text":true,"nodeType":true,"groups":true,"Pinned":true,"AgentBasedMethod":true},"propertyVersions":{"text":2,"codeName":1,"agentName":1,"valueName":1,"cssName":1,"HttpRoute":1,"uiName":1,"Label":1,"nodeType":2,"groups":1,"Pinned":15,"AgentBasedMethod":1},"properties":{"text":"Payment Method","codeName":"PaymentMethod","agentName":"PaymentMethod","valueName":"PaymentMethod","cssName":"payment-method","HttpRoute":"payment/method","uiName":"Payment Method","Label":"Payment Method","nodeType":"model","groups":{"group":"1a505e4a-939f-4b37-a418-0fe6beea68aa"},"Pinned":false,"AgentBasedMethod":false}},{"id":"1e55982c-0b6b-45c9-a250-1802f4269802","dirty":{"nodeType":true,"Pinned":true,"groupParent":true,"text":true,"uiAttributeType":true,"view-package":true,"Enumeration":true},"propertyVersions":{"text":2,"nodeType":1,"Pinned":1,"groupParent":1,"codeName":1,"agentName":1,"valueName":1,"cssName":1,"HttpRoute":1,"uiName":1,"Label":1,"uiAttributeType":1,"view-package":1,"Enumeration":1},"properties":{"text":"OneOf","nodeType":"attribute-property","Pinned":false,"groupParent":"81e6dc55-6553-42c5-9978-6dd764c8724c","codeName":"OneOf","agentName":"OneOf","valueName":"OneOf","cssName":"oneof","HttpRoute":"oneof","uiName":"OneOf","Label":"OneOf","uiAttributeType":"one-of","view-package":"526c5176-8a9a-449e-b17e-b4382745fc2f","Enumeration":"21b7a7c7-e12a-4f26-80b6-d26ee395b916"}},{"id":"47e15dca-756b-48f4-a7b8-11eaec6d207b","dirty":{"nodeType":true,"Pinned":true,"uiAttributeType":true,"groupParent":true,"text":true,"UseInView":true},"propertyVersions":{"text":2,"nodeType":1,"Pinned":7,"uiAttributeType":1,"groupParent":1,"codeName":1,"agentName":1,"valueName":1,"cssName":1,"HttpRoute":1,"uiName":1,"Label":1,"UseInView":1},"properties":{"text":"Name","nodeType":"model-property","Pinned":false,"uiAttributeType":"STRING","groupParent":"1a505e4a-939f-4b37-a418-0fe6beea68aa","codeName":"Name","agentName":"Name","valueName":"Name","cssName":"name","HttpRoute":"name","uiName":"Name","Label":"Name","UseInView":true}},{"id":"043ab222-348b-442f-b07e-26c523bbf975","dirty":{"nodeType":true,"Pinned":true,"uiAttributeType":true,"groupParent":true,"text":true,"groups":true,"UseInView":true},"propertyVersions":{"text":3,"nodeType":1,"Pinned":7,"uiAttributeType":1,"groupParent":1,"codeName":2,"agentName":2,"valueName":2,"cssName":2,"HttpRoute":2,"uiName":2,"Label":2,"groups":1,"UseInView":1},"properties":{"text":"Payment Method Type","nodeType":"model-property","Pinned":false,"uiAttributeType":"STRING","groupParent":"1a505e4a-939f-4b37-a418-0fe6beea68aa","codeName":"PaymentMethodType","agentName":"PaymentMethodType","valueName":"PaymentMethodType","cssName":"payment-method-type","HttpRoute":"payment/method/type","uiName":"Payment Method Type","Label":"Payment Method Type","groups":{"group":"81e6dc55-6553-42c5-9978-6dd764c8724c"},"UseInView":true}},{"id":"b7744016-972b-4876-b64a-4e04181cec32","dirty":{"nodeType":true,"Pinned":true,"groupParent":true,"text":true,"isDefaultProperty":true,"uiAttributeType":true},"propertyVersions":{"text":2,"nodeType":1,"Pinned":2,"groupParent":1,"codeName":1,"agentName":1,"valueName":1,"cssName":1,"HttpRoute":1,"uiName":1,"Label":1,"isDefaultProperty":1,"uiAttributeType":1},"properties":{"text":"Owner","nodeType":"model-property","Pinned":false,"groupParent":"1a505e4a-939f-4b37-a418-0fe6beea68aa","codeName":"Owner","agentName":"Owner","valueName":"Owner","cssName":"owner","HttpRoute":"owner","uiName":"Owner","Label":"Owner","isDefaultProperty":true,"uiAttributeType":"STRING"}},{"id":"c6721c7e-fed8-494f-8382-0e986758f7b2","dirty":{"nodeType":true,"Pinned":true,"groupParent":true,"text":true,"isDefaultProperty":true,"uiAttributeType":true},"propertyVersions":{"text":2,"nodeType":1,"Pinned":2,"groupParent":1,"codeName":1,"agentName":1,"valueName":1,"cssName":1,"HttpRoute":1,"uiName":1,"Label":1,"isDefaultProperty":1,"uiAttributeType":1},"properties":{"text":"Id","nodeType":"model-property","Pinned":false,"groupParent":"1a505e4a-939f-4b37-a418-0fe6beea68aa","codeName":"Id","agentName":"Id","valueName":"Id","cssName":"id","HttpRoute":"id","uiName":"Id","Label":"Id","isDefaultProperty":true,"uiAttributeType":"STRING"}},{"id":"87266e30-0b5e-4589-b217-62f1ae1b1e3a","dirty":{"nodeType":true,"Pinned":true,"groupParent":true,"text":true,"isDefaultProperty":true,"uiAttributeType":true},"propertyVersions":{"text":2,"nodeType":1,"Pinned":2,"groupParent":1,"codeName":1,"agentName":1,"valueName":1,"cssName":1,"HttpRoute":1,"uiName":1,"Label":1,"isDefaultProperty":1,"uiAttributeType":1},"properties":{"text":"Created","nodeType":"model-property","Pinned":false,"groupParent":"1a505e4a-939f-4b37-a418-0fe6beea68aa","codeName":"Created","agentName":"Created","valueName":"Created","cssName":"created","HttpRoute":"created","uiName":"Created","Label":"Created","isDefaultProperty":true,"uiAttributeType":"DATETIME"}},{"id":"a0bcffa7-d528-4d54-918f-b92fa1475372","dirty":{"nodeType":true,"Pinned":true,"groupParent":true,"text":true,"isDefaultProperty":true,"uiAttributeType":true},"propertyVersions":{"text":2,"nodeType":1,"Pinned":2,"groupParent":1,"codeName":1,"agentName":1,"valueName":1,"cssName":1,"HttpRoute":1,"uiName":1,"Label":1,"isDefaultProperty":1,"uiAttributeType":1},"properties":{"text":"Updated","nodeType":"model-property","Pinned":false,"groupParent":"1a505e4a-939f-4b37-a418-0fe6beea68aa","codeName":"Updated","agentName":"Updated","valueName":"Updated","cssName":"updated","HttpRoute":"updated","uiName":"Updated","Label":"Updated","isDefaultProperty":true,"uiAttributeType":"DATETIME"}},{"id":"27d9c6d8-0911-4c22-aeac-a426be4296c4","dirty":{"nodeType":true,"Pinned":true,"groupParent":true,"text":true,"isDefaultProperty":true,"uiAttributeType":true},"propertyVersions":{"text":2,"nodeType":1,"Pinned":2,"groupParent":1,"codeName":1,"agentName":1,"valueName":1,"cssName":1,"HttpRoute":1,"uiName":1,"Label":1,"isDefaultProperty":1,"uiAttributeType":1},"properties":{"text":"Deleted","nodeType":"model-property","Pinned":false,"groupParent":"1a505e4a-939f-4b37-a418-0fe6beea68aa","codeName":"Deleted","agentName":"Deleted","valueName":"Deleted","cssName":"deleted","HttpRoute":"deleted","uiName":"Deleted","Label":"Deleted","isDefaultProperty":true,"uiAttributeType":"BOOLEAN"}},{"id":"04b1c412-dea0-4b83-ac10-3eb09b9fdd1e","dirty":{"nodeType":true,"Pinned":true,"groupParent":true,"text":true,"isDefaultProperty":true,"uiAttributeType":true},"propertyVersions":{"text":2,"nodeType":1,"Pinned":4,"groupParent":1,"codeName":1,"agentName":1,"valueName":1,"cssName":1,"HttpRoute":1,"uiName":1,"Label":1,"isDefaultProperty":1,"uiAttributeType":1},"properties":{"text":"Version","nodeType":"model-property","Pinned":false,"groupParent":"1a505e4a-939f-4b37-a418-0fe6beea68aa","codeName":"Version","agentName":"Version","valueName":"Version","cssName":"version","HttpRoute":"version","uiName":"Version","Label":"Version","isDefaultProperty":true,"uiAttributeType":"INT"}}]}