{"links":[{"id":"fe6366cc-f9e1-471f-9005-93df9526ea44","source":"a0b77a37-072b-4e15-882d-b7beaf40bcd0","target":"0925c2b3-1047-4e59-b157-47868d75b4b9","properties":{"type":"property-link","property-link":{}}},{"id":"a5fc7776-83d3-4c0b-87e2-561741147d63","source":"a0b77a37-072b-4e15-882d-b7beaf40bcd0","target":"f370ea67-404f-46f9-95f3-8f9b6f35f828","properties":{"type":"property-link","property-link":{}}},{"id":"055273a5-dcec-4482-a025-bceb3db25259","source":"a0b77a37-072b-4e15-882d-b7beaf40bcd0","target":"197eaaf3-89b9-4f3f-b3cb-d286795eca32","properties":{"type":"property-link","property-link":{}}},{"id":"5d2c28d7-6951-4df9-8068-ace3d98eb59a","source":"a0b77a37-072b-4e15-882d-b7beaf40bcd0","target":"104e92a5-5c21-4a0b-866b-16253bef804c","properties":{"type":"property-link","property-link":{}}},{"id":"0033ee0f-7430-4816-91d8-85aa59ec5159","source":"a0b77a37-072b-4e15-882d-b7beaf40bcd0","target":"8f72b7eb-bc51-46d1-bb35-32e430fb1ee3","properties":{"type":"property-link","property-link":{}}},{"id":"a6ff22db-28ba-43bb-ae4c-e1502e603ccf","source":"a0b77a37-072b-4e15-882d-b7beaf40bcd0","target":"cd8df2e3-4324-4b70-8f32-db6a30cb1624","properties":{"type":"property-link","property-link":{}}},{"id":"1d04de9e-4e9e-4f8a-ba77-d4de336c8f62","source":"a0b77a37-072b-4e15-882d-b7beaf40bcd0","target":"2a3ed6c0-9a30-42ea-b5cd-71d36df22734","properties":{"type":"property-link","property-link":{}}},{"id":"5a33afbb-c4e0-447f-87e1-31dd88f0dc6d","source":"a0b77a37-072b-4e15-882d-b7beaf40bcd0","target":"4091e7df-ba1d-4740-b150-522fdc04b49c","properties":{"type":"property-link","property-link":{}}},{"id":"b6bff7ef-814b-48ac-91cf-6bd237dc3957","source":"3580759d-88d8-417c-a16e-4f662ecd3d17","target":"a0b77a37-072b-4e15-882d-b7beaf40bcd0","properties":{"type":"GeneralLink","GeneralLink":{}}}],"nodes":[{"id":"a0b77a37-072b-4e15-882d-b7beaf40bcd0","dirty":{"text":true,"nodeType":true,"groups":true,"hasLogicalChildren":true,"logicalChildrenTypes":true,"AgentBasedMethod":true,"Pinned":true},"propertyVersions":{"text":2,"codeName":1,"agentName":1,"valueName":1,"cssName":1,"HttpRoute":1,"uiName":1,"Label":1,"nodeType":1,"groups":1,"hasLogicalChildren":1,"logicalChildrenTypes":2,"AgentBasedMethod":3,"Pinned":6},"properties":{"text":"Category","codeName":"Category","agentName":"Category","valueName":"Category","cssName":"category","HttpRoute":"category","uiName":"Category","Label":"Category","nodeType":"model","groups":{"group":"21d52b70-cb3a-47ab-953c-7739b0a37d47"},"hasLogicalChildren":true,"logicalChildrenTypes":[],"AgentBasedMethod":false,"Pinned":false}},{"id":"0925c2b3-1047-4e59-b157-47868d75b4b9","dirty":{"nodeType":true,"Pinned":true,"uiAttributeType":true,"groupParent":true,"text":true},"propertyVersions":{"text":2,"nodeType":1,"Pinned":4,"uiAttributeType":1,"groupParent":1,"codeName":1,"agentName":1,"valueName":1,"cssName":1,"HttpRoute":1,"uiName":1,"Label":1},"properties":{"text":"Name","nodeType":"model-property","Pinned":false,"uiAttributeType":"STRING","groupParent":"21d52b70-cb3a-47ab-953c-7739b0a37d47","codeName":"Name","agentName":"Name","valueName":"Name","cssName":"name","HttpRoute":"name","uiName":"Name","Label":"Name"}},{"id":"f370ea67-404f-46f9-95f3-8f9b6f35f828","dirty":{"nodeType":true,"Pinned":true,"uiAttributeType":true,"groupParent":true,"text":true},"propertyVersions":{"text":2,"nodeType":1,"Pinned":4,"uiAttributeType":1,"groupParent":1,"codeName":1,"agentName":1,"valueName":1,"cssName":1,"HttpRoute":1,"uiName":1,"Label":1},"properties":{"text":"Description","nodeType":"model-property","Pinned":false,"uiAttributeType":"STRING","groupParent":"21d52b70-cb3a-47ab-953c-7739b0a37d47","codeName":"Description","agentName":"Description","valueName":"Description","cssName":"description","HttpRoute":"description","uiName":"Description","Label":"Description"}},{"id":"197eaaf3-89b9-4f3f-b3cb-d286795eca32","dirty":{"nodeType":true,"Pinned":true,"view-package":true,"groupParent":true,"text":true,"isDefaultProperty":true,"uiAttributeType":true},"propertyVersions":{"text":2,"nodeType":1,"Pinned":4,"view-package":1,"groupParent":1,"codeName":1,"agentName":1,"valueName":1,"cssName":1,"HttpRoute":1,"uiName":1,"Label":1,"isDefaultProperty":1,"uiAttributeType":1},"properties":{"text":"Owner","nodeType":"model-property","Pinned":false,"view-package":"d45835fe-b5b8-4134-abe1-1082cc66056a","groupParent":"21d52b70-cb3a-47ab-953c-7739b0a37d47","codeName":"Owner","agentName":"Owner","valueName":"Owner","cssName":"owner","HttpRoute":"owner","uiName":"Owner","Label":"Owner","isDefaultProperty":true,"uiAttributeType":"STRING"}},{"id":"104e92a5-5c21-4a0b-866b-16253bef804c","dirty":{"nodeType":true,"Pinned":true,"view-package":true,"groupParent":true,"text":true,"isDefaultProperty":true,"uiAttributeType":true},"propertyVersions":{"text":2,"nodeType":1,"Pinned":4,"view-package":1,"groupParent":1,"codeName":1,"agentName":1,"valueName":1,"cssName":1,"HttpRoute":1,"uiName":1,"Label":1,"isDefaultProperty":1,"uiAttributeType":1},"properties":{"text":"Id","nodeType":"model-property","Pinned":false,"view-package":"d45835fe-b5b8-4134-abe1-1082cc66056a","groupParent":"21d52b70-cb3a-47ab-953c-7739b0a37d47","codeName":"Id","agentName":"Id","valueName":"Id","cssName":"id","HttpRoute":"id","uiName":"Id","Label":"Id","isDefaultProperty":true,"uiAttributeType":"STRING"}},{"id":"8f72b7eb-bc51-46d1-bb35-32e430fb1ee3","dirty":{"nodeType":true,"Pinned":true,"view-package":true,"groupParent":true,"text":true,"isDefaultProperty":true,"uiAttributeType":true},"propertyVersions":{"text":2,"nodeType":1,"Pinned":4,"view-package":1,"groupParent":1,"codeName":1,"agentName":1,"valueName":1,"cssName":1,"HttpRoute":1,"uiName":1,"Label":1,"isDefaultProperty":1,"uiAttributeType":1},"properties":{"text":"Created","nodeType":"model-property","Pinned":false,"view-package":"d45835fe-b5b8-4134-abe1-1082cc66056a","groupParent":"21d52b70-cb3a-47ab-953c-7739b0a37d47","codeName":"Created","agentName":"Created","valueName":"Created","cssName":"created","HttpRoute":"created","uiName":"Created","Label":"Created","isDefaultProperty":true,"uiAttributeType":"DATETIME"}},{"id":"cd8df2e3-4324-4b70-8f32-db6a30cb1624","dirty":{"nodeType":true,"Pinned":true,"view-package":true,"groupParent":true,"text":true,"isDefaultProperty":true,"uiAttributeType":true},"propertyVersions":{"text":2,"nodeType":1,"Pinned":4,"view-package":1,"groupParent":1,"codeName":1,"agentName":1,"valueName":1,"cssName":1,"HttpRoute":1,"uiName":1,"Label":1,"isDefaultProperty":1,"uiAttributeType":1},"properties":{"text":"Updated","nodeType":"model-property","Pinned":false,"view-package":"d45835fe-b5b8-4134-abe1-1082cc66056a","groupParent":"21d52b70-cb3a-47ab-953c-7739b0a37d47","codeName":"Updated","agentName":"Updated","valueName":"Updated","cssName":"updated","HttpRoute":"updated","uiName":"Updated","Label":"Updated","isDefaultProperty":true,"uiAttributeType":"DATETIME"}},{"id":"2a3ed6c0-9a30-42ea-b5cd-71d36df22734","dirty":{"nodeType":true,"Pinned":true,"view-package":true,"groupParent":true,"text":true,"isDefaultProperty":true,"uiAttributeType":true},"propertyVersions":{"text":2,"nodeType":1,"Pinned":4,"view-package":1,"groupParent":1,"codeName":1,"agentName":1,"valueName":1,"cssName":1,"HttpRoute":1,"uiName":1,"Label":1,"isDefaultProperty":1,"uiAttributeType":1},"properties":{"text":"Deleted","nodeType":"model-property","Pinned":false,"view-package":"d45835fe-b5b8-4134-abe1-1082cc66056a","groupParent":"21d52b70-cb3a-47ab-953c-7739b0a37d47","codeName":"Deleted","agentName":"Deleted","valueName":"Deleted","cssName":"deleted","HttpRoute":"deleted","uiName":"Deleted","Label":"Deleted","isDefaultProperty":true,"uiAttributeType":"BOOLEAN"}},{"id":"4091e7df-ba1d-4740-b150-522fdc04b49c","dirty":{"nodeType":true,"Pinned":true,"view-package":true,"groupParent":true,"text":true,"isDefaultProperty":true,"uiAttributeType":true},"propertyVersions":{"text":2,"nodeType":1,"Pinned":4,"view-package":1,"groupParent":1,"codeName":1,"agentName":1,"valueName":1,"cssName":1,"HttpRoute":1,"uiName":1,"Label":1,"isDefaultProperty":1,"uiAttributeType":1},"properties":{"text":"Version","nodeType":"model-property","Pinned":false,"view-package":"d45835fe-b5b8-4134-abe1-1082cc66056a","groupParent":"21d52b70-cb3a-47ab-953c-7739b0a37d47","codeName":"Version","agentName":"Version","valueName":"Version","cssName":"version","HttpRoute":"version","uiName":"Version","Label":"Version","isDefaultProperty":true,"uiAttributeType":"INT"}},{"id":"3580759d-88d8-417c-a16e-4f662ecd3d17","dirty":{"text":true,"nodeType":true,"Pinned":true},"propertyVersions":{"text":2,"codeName":1,"agentName":1,"valueName":1,"cssName":1,"HttpRoute":1,"uiName":1,"Label":1,"nodeType":1,"Pinned":2},"properties":{"text":"General purpose attributes that can be used to categories for back office pricesses.","codeName":"Generalpurposeattributesthatcanbeusedtocategoriesforbackofficepricesses","agentName":"Generalpurposeattributesthatcanbeusedtocategoriesforbackofficepricesses","valueName":"Generalpurposeattributesthatcanbeusedtocategoriesforbackofficepricesses","cssName":"general-purpose-attributes-that-can-be-used-to-categories-for-back-office-pricesses","HttpRoute":"general/purpose/attributes/that/can/be/used/to/categories/for/back/office/pricesses.","uiName":"General purpose attributes that can be used to categories for back office pricesses.","Label":"General purpose attributes that can be used to categories for back office pricesses.","nodeType":"concept","Pinned":false}}]}